json_work_proof/__init__.py
json_work_proof/base64url.py
json_work_proof/classproperty.py
json_work_proof/json_encoder.py
json_work_proof-0.1.2.dist-info/METADATA
json_work_proof-0.1.2.dist-info/WHEEL
json_work_proof-0.1.2.dist-info/top_level.txt
json_work_proof-0.1.2.dist-info/RECORD
