Metadata-Version: 2.1
Name: json-work-proof
Version: 0.1.2
Summary: JSON Work Proof (JWP) - proof-of-work algorithm
Home-page: https://github.com/alexeichhorn/python-json-work-proof
Author: Alexander Eichhorn
Author-email: 
License: UNKNOWN
Platform: UNKNOWN
Classifier: Programming Language :: Python :: 3
Classifier: License :: OSI Approved :: MIT License
Classifier: Operating System :: OS Independent
Requires-Python: >=3.6
